lb_telemetry/__init__.py
lb_telemetry/__main__.py
lb_telemetry/py.typed
lb_telemetry-0.5.0.dist-info/LICENSE
lb_telemetry-0.5.0.dist-info/METADATA
lb_telemetry-0.5.0.dist-info/WHEEL
lb_telemetry-0.5.0.dist-info/entry_points.txt
lb_telemetry-0.5.0.dist-info/top_level.txt
lb_telemetry-0.5.0.dist-info/RECORD
