Metadata-Version: 2.1
Name: lb-telemetry
Version: 0.5.0
Summary: A utility for logging telemetry data from LHCb packages to MONIT
Author-email: Cameron McClymont <cameron.duncan.mcclymont@cern.ch>, Daniel Cervenkov <daniel.cervenkov@cern.ch>, Chris Burr <christopher.burr@cern.ch>
Project-URL: Homepage, https://gitlab.cern.ch/lhcb/lb-telemetry
Project-URL: Bug Tracker, https://gitlab.cern.ch/lhcb/lb-telemetry/issues
Classifier: Programming Language :: Python :: 3
Classifier: License :: OSI Approved :: GNU General Public License v3 (GPLv3)
Classifier: Operating System :: OS Independent
License-File: LICENSE
Requires-Dist: LbPlatformUtils
Requires-Dist: logzero
Requires-Dist: requests
Provides-Extra: dev
Requires-Dist: mypy ; extra == 'dev'
Requires-Dist: mypy-extensions ; extra == 'dev'
Requires-Dist: pre-commit ; extra == 'dev'
Requires-Dist: pytest ; extra == 'dev'
Requires-Dist: pytest-cov ; extra == 'dev'
Requires-Dist: ruff ; extra == 'dev'
Requires-Dist: types-requests ; extra == 'dev'
